{
  "version": "62.0",
  "nodes": {
    "LOAD_DATASET0": {
      "action": "load",
      "parameters": {
        "dataset": {
          "label": "C360 eDM Master",
          "name": "C360_eDM_Master",
          "type": "analyticsDataset"
        },
        "fields": [
          "Email",
          "Personalization_1__c",
          "Send_timestamp_string",
          "Personalization_3__c",
          "KurtID",
          "Personalization_20__c",
          "CampaignName",
          "MobilePhone",
          "Personalization_15__c",
          "Personalization_13__c",
          "Personalization_17__c",
          "Personalization_7__c",
          "Personalization_9__c",
          "Personalization_19__c",
          "Personalization_5__c",
          "Personalization_11__c",
          "AccountID",
          "Personalization_2__c",
          "ContactID",
          "CampaignCD",
          "Send_timestamp",
          "Personalization_12__c",
          "Personalization_14__c",
          "Personalization_16__c",
          "CampaignID",
          "Personalization_8__c",
          "Personalization_18__c",
          "Personalization_6__c",
          "Personalization_4__c",
          "Personalization_10__c"
        ],
        "sampleDetails": {
          "sortBy": [],
          "type": "TopN"
        }
      },
      "sources": []
    },
    "OUTPUT0": {
      "action": "save",
      "parameters": {
        "dataset": {
          "folderName": "Campaign_Developer_App",
          "label": "C360_eDM_Master",
          "name": "C360_eDM_Master",
          "type": "analyticsDataset"
        },
        "fields": [],
        "measuresToCurrencies": []
      },
      "sources": [
        "APPEND6"
      ]
    },
    "LOAD_DATASET1": {
      "action": "load",
      "parameters": {
        "dataset": {
          "label": "C360 - MC - Always On - Onboarding new Mobil Tale kunde",
          "name": "C360_MC_Always_On_Onboarding_new_Mobil_Tale_kunde",
          "type": "analyticsDataset"
        },
        "fields": [
          "Transform1.Personalization_20__c",
          "Send_timestamp_string",
          "Primarymed.Email",
          "Transform1.Transform1.CampaignName",
          "Transform1.CampaignCD",
          "Transform1.Personalization_3__c",
          "Send_timestamp",
          "Primarymed.MobilePhone",
          "Transform1.Transform1.Id",
          "Transform1.Personalization_1__c",
          "Transform1.Personalization_2__c",
          "Transform1.Transform7.KurtID__c",
          "Transform1.Personalization_4__c",
          "Transform1.Personalization_5__c",
          "Primarymed.Id",
          "Transform1.Transform7.Id"
        ],
        "sampleDetails": {
          "sortBy": [],
          "type": "TopN"
        }
      },
      "sources": []
    },
    "LOAD_DATASET3": {
      "action": "load",
      "parameters": {
        "dataset": {
          "label": "C360 - MC - Always On - Nysalg Fiber ved ikke svar",
          "name": "Withdrawn_by_dialer",
          "type": "analyticsDataset"
        },
        "fields": [
          "PrimaryCon.Id",
          "Personalization_1__c",
          "Personalization_2__c",
          "Send_timestamp_string",
          "Personalization_3__c",
          "C360_96.Id",
          "Campaign_cd",
          "PrimaryCon.Email",
          "Send_timestamp",
          "Account.Id",
          "Account.KurtID__c",
          "C360_96.CampaignName",
          "PrimaryCon.MobilePhone"
        ],
        "sampleDetails": {
          "sortBy": [],
          "type": "TopN"
        }
      },
      "sources": []
    },
    "LOAD_DATASET4": {
      "action": "load",
      "parameters": {
        "dataset": {
          "label": "C360 - MC - Always On - Rebinding Fiber ved ikke svar",
          "name": "C360_MC_Always_On_Rebinding_Fiber_ved_ikke_svar",
          "type": "analyticsDataset"
        },
        "fields": [
          "Beregnedef.PrimaryCon.Email",
          "Beregnedef.Send_timestamp",
          "Personalization_1__c",
          "Join8.Personalization_3__c",
          "Beregnedef.Account.KurtID__c",
          "Beregnedef.PrimaryCon.MobilePhone",
          "Beregnedef.PrimaryCon.Id",
          "Join8.Personalization_2__c",
          "Beregnedef.Campaign_cd",
          "Beregnedef.C360_96.CampaignName",
          "Beregnedef.Send_timestamp_string",
          "Beregnedef.C360_96.Id",
          "Beregnedef.Account.Id"
        ],
        "sampleDetails": {
          "sortBy": [],
          "type": "TopN"
        }
      },
      "sources": []
    },
    "LOAD_DATASET5": {
      "action": "load",
      "parameters": {
        "dataset": {
          "label": "C360 - MC - Always On - Onboarding new SZMobil kunde oppsalg oppdatert",
          "name": "C360_MC_Always_On_Onboarding_new_SZMobil_kunde_oppsalg_oppdatert",
          "type": "analyticsDataset"
        },
        "fields": [
          "PrimaryCon.Id",
          "Personalization_1__c",
          "Personalization_2__c",
          "Send_timestamp_string",
          "Personalization_3__c",
          "C360_143.Id",
          "Campaign_CD",
          "KurtID__c",
          "PrimaryCon.Email",
          "Send_timestamp",
          "Personaliz.Personalization_5__c",
          "C360_143.Name",
          "Personalization_4__c",
          "Id",
          "PrimaryCon.MobilePhone"
        ],
        "sampleDetails": {
          "sortBy": [],
          "type": "TopN"
        }
      },
      "sources": []
    },
    "APPEND0": {
      "action": "appendV2",
      "parameters": {
        "fieldMappings": [
          {
            "bottom": "Primarymed.Email",
            "top": "Email"
          },
          {
            "bottom": "Transform1.Personalization_1__c",
            "top": "Personalization_1__c"
          },
          {
            "bottom": "Send_timestamp_string",
            "top": "Send_timestamp_string"
          },
          {
            "bottom": "Transform1.Personalization_3__c",
            "top": "Personalization_3__c"
          },
          {
            "bottom": "Transform1.Transform7.KurtID__c",
            "top": "KurtID"
          },
          {
            "bottom": "Transform1.Personalization_20__c",
            "top": "Personalization_20__c"
          },
          {
            "bottom": "Transform1.Transform1.CampaignName",
            "top": "CampaignName"
          },
          {
            "bottom": "Primarymed.MobilePhone",
            "top": "MobilePhone"
          },
          {
            "bottom": "Transform1.Personalization_5__c",
            "top": "Personalization_5__c"
          },
          {
            "bottom": "Transform1.Transform7.Id",
            "top": "AccountID"
          },
          {
            "bottom": "Transform1.Personalization_2__c",
            "top": "Personalization_2__c"
          },
          {
            "bottom": "Primarymed.Id",
            "top": "ContactID"
          },
          {
            "bottom": "Transform1.CampaignCD",
            "top": "CampaignCD"
          },
          {
            "bottom": "Send_timestamp",
            "top": "Send_timestamp"
          },
          {
            "bottom": "Transform1.Transform1.Id",
            "top": "CampaignID"
          },
          {
            "bottom": "Transform1.Personalization_4__c",
            "top": "Personalization_4__c"
          }
        ]
      },
      "sources": [
        "LOAD_DATASET0",
        "LOAD_DATASET1"
      ]
    },
    "LOAD_DATASET6": {
      "action": "load",
      "parameters": {
        "dataset": {
          "label": "C360 - MC - Always On - Onboarding new SafeZoneMobil kunde",
          "name": "C360_MC_Always_On_Onboarding_new_SafeZoneMobil_kunde",
          "type": "analyticsDataset"
        },
        "fields": [
          "AccountID",
          "Email",
          "Send_timestamp_string",
          "Transform9.Transform8.aftersuppr.Transform7.Personalization_2__c",
          "Transform9.Transform8.aftersuppr.Transform7.Personalization_1__c",
          "KurtID",
          "Transform9.Transform8.aftersuppr.Transform7.Personalization_3__c",
          "Transform9.Transform8.aftersuppr.Transform7.Personalization_6__c",
          "Transform9.Transform8.aftersuppr.Transform7.Personalization_5__c",
          "CampaignName",
          "ContactID",
          "MobilePhone",
          "Transform9.CampaignCD",
          "Send_timestamp",
          "CampaignID",
          "Transform9.Transform8.Personalization_4__c",
          "Transform9.Personalization_7__c",
          "Transform9.Personalization_8"
        ],
        "sampleDetails": {
          "sortBy": [],
          "type": "TopN"
        }
      },
      "sources": []
    },
    "APPEND1": {
      "action": "appendV2",
      "parameters": {
        "fieldMappings": [
          {
            "bottom": "Email",
            "top": "Email"
          },
          {
            "bottom": "Transform9.Transform8.aftersuppr.Transform7.Personalization_1__c",
            "top": "Personalization_1__c"
          },
          {
            "bottom": "Send_timestamp_string",
            "top": "Send_timestamp_string"
          },
          {
            "bottom": "Transform9.Transform8.aftersuppr.Transform7.Personalization_3__c",
            "top": "Personalization_3__c"
          },
          {
            "bottom": "KurtID",
            "top": "KurtID"
          },
          {
            "bottom": "CampaignName",
            "top": "CampaignName"
          },
          {
            "bottom": "MobilePhone",
            "top": "MobilePhone"
          },
          {
            "bottom": "Transform9.Personalization_7__c",
            "top": "Personalization_7__c"
          },
          {
            "bottom": "Transform9.Transform8.aftersuppr.Transform7.Personalization_5__c",
            "top": "Personalization_5__c"
          },
          {
            "bottom": "AccountID",
            "top": "AccountID"
          },
          {
            "bottom": "Transform9.Transform8.aftersuppr.Transform7.Personalization_2__c",
            "top": "Personalization_2__c"
          },
          {
            "bottom": "ContactID",
            "top": "ContactID"
          },
          {
            "bottom": "Transform9.CampaignCD",
            "top": "CampaignCD"
          },
          {
            "bottom": "Send_timestamp",
            "top": "Send_timestamp"
          },
          {
            "bottom": "CampaignID",
            "top": "CampaignID"
          },
          {
            "bottom": "Transform9.Personalization_8",
            "top": "Personalization_8__c"
          },
          {
            "bottom": "Transform9.Transform8.aftersuppr.Transform7.Personalization_6__c",
            "top": "Personalization_6__c"
          },
          {
            "bottom": "Transform9.Transform8.Personalization_4__c",
            "top": "Personalization_4__c"
          }
        ]
      },
      "sources": [
        "APPEND0",
        "LOAD_DATASET6"
      ]
    },
    "APPEND2": {
      "action": "appendV2",
      "parameters": {
        "fieldMappings": [
          {
            "bottom": "PrimaryCon.Email",
            "top": "Email"
          },
          {
            "bottom": "Personalization_1__c",
            "top": "Personalization_1__c"
          },
          {
            "bottom": "Send_timestamp_string",
            "top": "Send_timestamp_string"
          },
          {
            "bottom": "Personalization_3__c",
            "top": "Personalization_3__c"
          },
          {
            "bottom": "KurtID__c",
            "top": "KurtID"
          },
          {
            "bottom": "C360_143.Name",
            "top": "CampaignName"
          },
          {
            "bottom": "PrimaryCon.MobilePhone",
            "top": "MobilePhone"
          },
          {
            "bottom": "Personaliz.Personalization_5__c",
            "top": "Personalization_5__c"
          },
          {
            "bottom": "Id",
            "top": "AccountID"
          },
          {
            "bottom": "Personalization_2__c",
            "top": "Personalization_2__c"
          },
          {
            "bottom": "PrimaryCon.Id",
            "top": "ContactID"
          },
          {
            "bottom": "Campaign_CD",
            "top": "CampaignCD"
          },
          {
            "bottom": "Send_timestamp",
            "top": "Send_timestamp"
          },
          {
            "bottom": "C360_143.Id",
            "top": "CampaignID"
          },
          {
            "bottom": "Personalization_4__c",
            "top": "Personalization_4__c"
          }
        ]
      },
      "sources": [
        "APPEND1",
        "LOAD_DATASET5"
      ]
    },
    "APPEND3": {
      "action": "appendV2",
      "parameters": {
        "fieldMappings": [
          {
            "bottom": "Beregnedef.PrimaryCon.Email",
            "top": "Email"
          },
          {
            "bottom": "Personalization_1__c",
            "top": "Personalization_1__c"
          },
          {
            "bottom": "Beregnedef.Send_timestamp_string",
            "top": "Send_timestamp_string"
          },
          {
            "bottom": "Join8.Personalization_3__c",
            "top": "Personalization_3__c"
          },
          {
            "bottom": "Beregnedef.Account.KurtID__c",
            "top": "KurtID"
          },
          {
            "bottom": "Beregnedef.C360_96.CampaignName",
            "top": "CampaignName"
          },
          {
            "bottom": "Beregnedef.PrimaryCon.MobilePhone",
            "top": "MobilePhone"
          },
          {
            "bottom": "Beregnedef.Account.Id",
            "top": "AccountID"
          },
          {
            "bottom": "Join8.Personalization_2__c",
            "top": "Personalization_2__c"
          },
          {
            "bottom": "Beregnedef.PrimaryCon.Id",
            "top": "ContactID"
          },
          {
            "bottom": "Beregnedef.Campaign_cd",
            "top": "CampaignCD"
          },
          {
            "bottom": "Beregnedef.Send_timestamp",
            "top": "Send_timestamp"
          },
          {
            "bottom": "Beregnedef.C360_96.Id",
            "top": "CampaignID"
          }
        ]
      },
      "sources": [
        "APPEND2",
        "LOAD_DATASET4"
      ]
    },
    "APPEND4": {
      "action": "appendV2",
      "parameters": {
        "fieldMappings": [
          {
            "bottom": "PrimaryCon.Email",
            "top": "Email"
          },
          {
            "bottom": "Personalization_1__c",
            "top": "Personalization_1__c"
          },
          {
            "bottom": "Send_timestamp_string",
            "top": "Send_timestamp_string"
          },
          {
            "bottom": "Personalization_3__c",
            "top": "Personalization_3__c"
          },
          {
            "bottom": "Account.KurtID__c",
            "top": "KurtID"
          },
          {
            "bottom": "C360_96.CampaignName",
            "top": "CampaignName"
          },
          {
            "bottom": "PrimaryCon.MobilePhone",
            "top": "MobilePhone"
          },
          {
            "bottom": "Account.Id",
            "top": "AccountID"
          },
          {
            "bottom": "Personalization_2__c",
            "top": "Personalization_2__c"
          },
          {
            "bottom": "PrimaryCon.Id",
            "top": "ContactID"
          },
          {
            "bottom": "Campaign_cd",
            "top": "CampaignCD"
          },
          {
            "bottom": "Send_timestamp",
            "top": "Send_timestamp"
          },
          {
            "bottom": "C360_96.Id",
            "top": "CampaignID"
          }
        ]
      },
      "sources": [
        "APPEND3",
        "LOAD_DATASET3"
      ]
    },
    "LOAD_DATASET7": {
      "action": "load",
      "parameters": {
        "dataset": {
          "label": "C360 - MC - Always On - Fiber nysalg - Har fiber gjennom utleier_3.part",
          "name": "C360_MC_Always_On_Fiber_nysalg_Har_fiber_gjennom_utleier_3_part",
          "type": "analyticsDataset"
        },
        "fields": [
          "Account.SEogAgrol.Id",
          "PrimaryCon.Id",
          "Send_timestamp",
          "Personalization_1__c",
          "Send_timestamp_string",
          "Account.SEogAgrol.KurtID__c",
          "C360_96.Id",
          "C360_96.CampaignName",
          "Campaign_cd",
          "PrimaryCon.MobilePhone",
          "PrimaryCon.Email"
        ],
        "sampleDetails": {
          "sortBy": [],
          "type": "TopN"
        }
      },
      "sources": []
    },
    "APPEND5": {
      "action": "appendV2",
      "parameters": {
        "fieldMappings": [
          {
            "bottom": "PrimaryCon.Email",
            "top": "Email"
          },
          {
            "bottom": "Personalization_1__c",
            "top": "Personalization_1__c"
          },
          {
            "bottom": "Send_timestamp_string",
            "top": "Send_timestamp_string"
          },
          {
            "bottom": "Account.SEogAgrol.KurtID__c",
            "top": "KurtID"
          },
          {
            "bottom": "C360_96.CampaignName",
            "top": "CampaignName"
          },
          {
            "bottom": "PrimaryCon.MobilePhone",
            "top": "MobilePhone"
          },
          {
            "bottom": "Account.SEogAgrol.Id",
            "top": "AccountID"
          },
          {
            "bottom": "PrimaryCon.Id",
            "top": "ContactID"
          },
          {
            "bottom": "Campaign_cd",
            "top": "CampaignCD"
          },
          {
            "bottom": "Send_timestamp",
            "top": "Send_timestamp"
          },
          {
            "bottom": "C360_96.Id",
            "top": "CampaignID"
          }
        ]
      },
      "sources": [
        "APPEND4",
        "LOAD_DATASET7"
      ]
    },
    "LOAD_DATASET8": {
      "action": "load",
      "parameters": {
        "dataset": {
          "label": "C360 - MC - Always On - Velkomstprogram nye medlemmer Forbund",
          "name": "C360_MC_Always_On_Velkomstprogram_nye_medlemmer_Forbund",
          "type": "analyticsDataset"
        },
        "fields": [
          "UniqueCont.MobilePhone",
          "Send_timestamp",
          "C360_44.Id",
          "Send_timestamp_string",
          "UniqueCont.Email",
          "C360_44.Name",
          "Personalization_1",
          "Id",
          "Personalization_2",
          "UniqueCont.Id",
          "Campaign_CD",
          "KurtID__c"
        ],
        "sampleDetails": {
          "sortBy": [],
          "type": "TopN"
        }
      },
      "sources": []
    },
    "APPEND6": {
      "action": "appendV2",
      "parameters": {
        "fieldMappings": [
          {
            "bottom": "UniqueCont.Email",
            "top": "Email"
          },
          {
            "bottom": "Personalization_1",
            "top": "Personalization_1__c"
          },
          {
            "bottom": "Send_timestamp_string",
            "top": "Send_timestamp_string"
          },
          {
            "bottom": "KurtID__c",
            "top": "KurtID"
          },
          {
            "bottom": "C360_44.Name",
            "top": "CampaignName"
          },
          {
            "bottom": "UniqueCont.MobilePhone",
            "top": "MobilePhone"
          },
          {
            "bottom": "Id",
            "top": "AccountID"
          },
          {
            "bottom": "Personalization_2",
            "top": "Personalization_2__c"
          },
          {
            "bottom": "UniqueCont.Id",
            "top": "ContactID"
          },
          {
            "bottom": "Campaign_CD",
            "top": "CampaignCD"
          },
          {
            "bottom": "Send_timestamp",
            "top": "Send_timestamp"
          },
          {
            "bottom": "C360_44.Id",
            "top": "CampaignID"
          }
        ]
      },
      "sources": [
        "APPEND5",
        "LOAD_DATASET8"
      ]
    }
  },
  "ui": {
    "nodes": {
      "LOAD_DATASET0": {
        "label": "C360 eDM Master",
        "type": "LOAD_DATASET",
        "top": 112,
        "left": 112,
        "parameters": {
          "sampleSize": 2000
        }
      },
      "OUTPUT0": {
        "label": "C360_eDM_Master",
        "description": "",
        "type": "OUTPUT",
        "top": 112.30000000000001,
        "left": 1231.3
      },
      "LOAD_DATASET1": {
        "label": "C360 - MC - Always On - Onboarding new Mobil Tale kunde",
        "type": "LOAD_DATASET",
        "top": 252,
        "left": 112,
        "parameters": {
          "sampleSize": 2000
        }
      },
      "LOAD_DATASET3": {
        "label": "C360 - MC - Always On - Nysalg Fiber ved ikke svar",
        "type": "LOAD_DATASET",
        "top": 813.3,
        "left": 113.19999999999999,
        "parameters": {
          "sampleSize": 2000
        }
      },
      "LOAD_DATASET4": {
        "label": "C360 - MC - Always On - Rebinding Fiber ved ikke svar",
        "type": "LOAD_DATASET",
        "top": 672.1,
        "left": 111.9,
        "parameters": {
          "sampleSize": 2000
        }
      },
      "LOAD_DATASET5": {
        "label": "C360 - MC - Always On - Onboarding new SZMobil kunde oppsalg oppdatert",
        "type": "LOAD_DATASET",
        "top": 532.2,
        "left": 112,
        "parameters": {
          "sampleSize": 2000
        }
      },
      "APPEND0": {
        "label": "Append 0",
        "type": "APPEND",
        "top": 112,
        "left": 252
      },
      "LOAD_DATASET6": {
        "label": "C360 - MC - Always On - Onboarding new SafeZoneMobil kunde",
        "type": "LOAD_DATASET",
        "top": 392,
        "left": 112,
        "parameters": {
          "sampleSize": 2000
        }
      },
      "APPEND1": {
        "label": "Append 1",
        "type": "APPEND",
        "top": 112,
        "left": 392
      },
      "APPEND2": {
        "label": "Append 2",
        "type": "APPEND",
        "top": 112,
        "left": 532
      },
      "APPEND3": {
        "label": "Append 3",
        "type": "APPEND",
        "top": 112,
        "left": 672
      },
      "APPEND4": {
        "label": "Append 4",
        "type": "APPEND",
        "top": 112,
        "left": 812
      },
      "LOAD_DATASET7": {
        "label": "C360 - MC - Always On - Fiber nysalg - Har fiber gjennom utleier_3.part",
        "type": "LOAD_DATASET",
        "top": 953.3,
        "left": 112,
        "parameters": {
          "sampleSize": 2000
        }
      },
      "APPEND5": {
        "label": "Append 5",
        "type": "APPEND",
        "top": 111.9,
        "left": 952
      },
      "LOAD_DATASET8": {
        "label": "C360 - MC - Always On - Velkomstprogram nye medlemmer Forbund",
        "type": "LOAD_DATASET",
        "top": 251.8,
        "left": 1092,
        "parameters": {
          "sampleSize": 2000
        }
      },
      "APPEND6": {
        "label": "Append 6",
        "type": "APPEND",
        "top": 112.1,
        "left": 1092
      }
    },
    "connectors": [
      {
        "source": "LOAD_DATASET0",
        "target": "APPEND0"
      },
      {
        "source": "APPEND0",
        "target": "APPEND1"
      },
      {
        "source": "LOAD_DATASET6",
        "target": "APPEND1"
      },
      {
        "source": "APPEND1",
        "target": "APPEND2"
      },
      {
        "source": "LOAD_DATASET5",
        "target": "APPEND2"
      },
      {
        "source": "APPEND2",
        "target": "APPEND3"
      },
      {
        "source": "LOAD_DATASET4",
        "target": "APPEND3"
      },
      {
        "source": "APPEND3",
        "target": "APPEND4"
      },
      {
        "source": "LOAD_DATASET3",
        "target": "APPEND4"
      },
      {
        "source": "APPEND6",
        "target": "OUTPUT0"
      },
      {
        "source": "APPEND4",
        "target": "APPEND5"
      },
      {
        "source": "LOAD_DATASET7",
        "target": "APPEND5"
      },
      {
        "source": "APPEND5",
        "target": "APPEND6"
      },
      {
        "source": "LOAD_DATASET8",
        "target": "APPEND6"
      },
      {
        "source": "LOAD_DATASET1",
        "target": "APPEND0"
      }
    ],
    "hiddenColumns": []
  }
}